repacolors/__init__.py
repacolors/blend.py
repacolors/colors.py
repacolors/command/repacolor.py
repacolors/convert.py
repacolors/css-color-names.json
repacolors/cubehelix.py
repacolors/distance.py
repacolors/documentation.md
repacolors/ops.py
repacolors/palette/__init__.py
repacolors/palette/colorbrewer.py
repacolors/picker.py
repacolors/scale.py
repacolors/schemes.py
repacolors/terminal.py
repacolors/themes/__init__.py
repacolors/themes/theme.py
repacolors/themes/xresources.py
repacolors/types.py
repacolors-0.8.0.dist-info/entry_points.txt
repacolors-0.8.0.dist-info/LICENSE
repacolors-0.8.0.dist-info/WHEEL
repacolors-0.8.0.dist-info/METADATA
repacolors-0.8.0.dist-info/RECORD
